Metadata-Version: 2.1
Name: fhirbase
Version: 0.0.1
Summary: fhirbase connector
Home-page: http://github.com/fhirbase/fhirbase.py
Author: HealthSamurai
Author-email: fhirbase.py@health-samurai.io
License: UNKNOWN
Keywords: fhir,fhirbase
Platform: UNKNOWN
Classifier: Development Status :: 4 - Beta
Classifier: Environment :: Web Environment
Classifier: Intended Audience :: Developers
Classifier: Operating System :: OS Independent
Classifier: Programming Language :: Python
Classifier: Programming Language :: Python :: 3
Classifier: Programming Language :: Python :: 3.4
Classifier: Programming Language :: Python :: 3.5
Classifier: Programming Language :: Python :: 3.6
Classifier: Topic :: Internet :: WWW/HTTP
Classifier: Topic :: Database :: Front-Ends
Classifier: Topic :: Software Development :: Libraries :: Python Modules
